cgtp_cli/__init__.py
cgtp_cli/__main__.py
cgtp_cli/chatGPT.py
cgtp_cli/cli.py
cgtp_cli-1.0.3.dist-info/LICENSE
cgtp_cli-1.0.3.dist-info/METADATA
cgtp_cli-1.0.3.dist-info/WHEEL
cgtp_cli-1.0.3.dist-info/entry_points.txt
cgtp_cli-1.0.3.dist-info/top_level.txt
cgtp_cli-1.0.3.dist-info/RECORD
