Metadata-Version: 2.1
Name: cgtp-cli
Version: 1.0.3
Summary: This is a command line application that allows you to ask ChatGPT about a command you need.
Author: Edwinsn
Author-email: edwinsanchez750@gmail.com
License-File: LICENSE
Requires-Dist: openai (>=0.27.0)
